rss_cli/.DS_Store
rss_cli/__init__.py
rss_cli/__main__.py
rss_cli/app.py
rss_cli/data/__init__.py
rss_cli/data/config.py
rss_cli/models/__init__.py
rss_cli/models/rss_model.py
rss_cli/widgets/__init__.py
rss_cli/widgets/article.py
rss_cli/widgets/base_class.py
rss_cli/widgets/rss_table.py
rss_cli/widgets/user_input.py
rss_cli-0.1.3.1.dist-info/METADATA
rss_cli-0.1.3.1.dist-info/WHEEL
rss_cli-0.1.3.1.dist-info/entry_points.txt
rss_cli-0.1.3.1.dist-info/RECORD
